<?xml version="1.0" encoding="utf-8"?>
<LanguageData>
  <!--The following translations were generated by https://www.deepl.com/-->
  <!-- EN: corrupt chi -->
  <CorruptChi.label>腐化气</CorruptChi.label>
  <!-- EN: Throw a ball full of corrupt chi against a singular target. Very effective against boss-like entities. -->
  <CorruptChi.description>向单一目标投掷一颗充满腐化气场的球体。对类似BOSS的实体非常有效。</CorruptChi.description>
  <!-- EN: crows leap -->
  <CrowsLeap.label>乌鸦之跃</CrowsLeap.label>
  <!-- EN: Leap through distant location, exuding crow feathers and dark energy during propultion. -->
  <CrowsLeap.description>跃向遥远之地，在推进过程中散发出乌鸦羽毛和黑暗能量。</CrowsLeap.description>
  <!-- EN: gravity jump -->
  <CrowsLeap.verbProperties.label>重力跳跃</CrowsLeap.verbProperties.label>
  <!-- EN: dark knife -->
  <DarkKnife.label>黑暗之刃</DarkKnife.label>
  <!-- EN: Throw a dangerously sharp knife against a singular distant enemy, inflicting armor bane upon impact. -->
  <DarkKnife.description>向远处单个敌人投掷一把锋利得危险的匕首，命中时将造成“护甲克星”效果。</DarkKnife.description>
  <!-- EN: dark shuriken -->
  <DarkShuriken.label>黑暗手里剑</DarkShuriken.label>
  <!-- EN: Throw a big shuriken that explodes upon impact, where it can take out groups of enemies and weakens them if they survived the blast. -->
  <DarkShuriken.description>投掷一枚巨大的手里剑，它会在撞击时爆炸，能够一举消灭成群的敌人，并削弱那些幸免于爆炸的敌人。</DarkShuriken.description>
  <!-- EN: dark spear -->
  <DarkSpear.label>黑暗长矛</DarkSpear.label>
  <!-- EN: Throw a dangerously sharp spear against a singular distant enemy. -->
  <DarkSpear.description>向远处单个敌人投掷一支锋利得令人胆寒的长矛。</DarkSpear.description>
  <!-- EN: phantom of death -->
  <PhantomOfDeath.label>死亡幽灵</PhantomOfDeath.label>
  <!-- EN: Shroud yourself with the essence of death, granting you a passive ability of inflicting instant death damage on melee hit. -->
  <PhantomOfDeath.description>用死亡之精髓包裹自己，使你获得一项被动能力：近战命中时可造成即死伤害。</PhantomOfDeath.description>
  <!-- EN: shadow cloak -->
  <ShadowCloak.label>暗影斗篷</ShadowCloak.label>
  <!-- EN: Render yourself invisible, while boosting your melee potential. -->
  <ShadowCloak.description>使自己隐形，同时提升近战能力。</ShadowCloak.description>
  <!-- EN: shuriken throw -->
  <Shuriken.label>手里剑投掷</Shuriken.label>
  <!-- EN: Throw a dangerously sharp shuriken on a distant enemy. -->
  <Shuriken.description>向远处的敌人投掷一枚锋利得令人胆寒的手里剑。</Shuriken.description>
  <!-- EN: socialize -->
  <Socialize.label>社交</Socialize.label>
  <!-- EN: Use your good looks and silver tongue to improve their opinion on you. -->
  <Socialize.description>利用你的英俊外貌和巧舌如簧，提升他们对你的好感。</Socialize.description>
  <!-- EN: summon automatons -->
  <SummonAutomatons.label>召唤自动机</SummonAutomatons.label>
  <!-- EN: Summon automaton soldiers directly at the enemy to fight alongside you. Must be target at an enemy pawn. -->
  <SummonAutomatons.description>直接在敌人身边召唤自动机士兵，让他们与你并肩作战。必须将敌人角色作为目标。</SummonAutomatons.description>
  <!-- EN: summon ballista -->
  <SummonBallista.label>召唤弩炮</SummonBallista.label>
  <!-- EN: Summon a ballista turret that can provide cover fire for you. -->
  <SummonBallista.description>召唤一座弩炮塔，它能为你提供掩护火力。</SummonBallista.description>
  <!-- EN: summon dark mine -->
  <SummonDarkMine.label>召唤黑暗矿井</SummonDarkMine.label>
  <!-- EN: Summon a dark mine rune in medium distance, which explodes when triggered. -->
  <SummonDarkMine.description>在中等距离处召唤一枚黑暗地雷符文，触发后会爆炸。</SummonDarkMine.description>
  <!-- EN: summon decoy -->
  <SummonDecoy.label>召唤诱饵</SummonDecoy.label>
  <!-- EN: Summon an annoying decoy that draws the aggro of multiple enemies, where upon destruction, the dummy will explode. -->
  <SummonDecoy.description>召唤一个烦人的诱饵，吸引多个敌人的仇恨；该诱饵被摧毁后会发生爆炸。</SummonDecoy.description>
</LanguageData>
